{
    "code": 0,
    "data": {
        "hotkey": [
            {
                "k": "无条件 ",
                "n": 85228
            },
            {
                "k": "双世宠妃 ",
                "n": 81282
            },
            {
                "k": "从前慢 ",
                "n": 78055
            },
            {
                "k": "王俊凯 ",
                "n": 70432
            },
            {
                "k": "李宇春 ",
                "n": 65388
            },
            {
                "k": "林忆莲 ",
                "n": 60861
            },
            {
                "k": "悟空传 ",
                "n": 59666
            },
            {
                "k": "淘汰 ",
                "n": 43617
            },
            {
                "k": "TIME ",
                "n": 39694
            },
            {
                "k": "紫 ",
                "n": 26260
            },
            {
                "k": "九张机 ",
                "n": 25309
            },
            {
                "k": "非酋 薛明媛/朱贺 ",
                "n": 18997
            },
            {
                "k": "四年半 ",
                "n": 16146
            },
            {
                "k": "远走高飞 ",
                "n": 15043
            },
            {
                "k": "我的前半生 ",
                "n": 14012
            },
            {
                "k": "风一样的我 ",
                "n": 13715
            },
            {
                "k": "WHAT ARE WORDS ",
                "n": 13604
            },
            {
                "k": "醉玲珑 ",
                "n": 12607
            },
            {
                "k": "法克油 7妹 ",
                "n": 12130
            },
            {
                "k": "谢谢侬 陈奕迅 ",
                "n": 10858
            },
            {
                "k": "流着泪说分手 ",
                "n": 10856
            },
            {
                "k": "雀跃 ",
                "n": 10775
            },
            {
                "k": "舍得 ",
                "n": 9980
            },
            {
                "k": "一生所爱 卢冠廷 ",
                "n": 9187
            },
            {
                "k": "中国好声音 第六季 ",
                "n": 8858
            },
            {
                "k": "DJ舞曲(华语)系列5 DJ ",
                "n": 8741
            },
            {
                "k": "小青龙 ",
                "n": 8719
            },
            {
                "k": "我的小可爱 ",
                "n": 8625
            },
            {
                "k": "叶炫清 ",
                "n": 8582
            },
            {
                "k": "沧海一声笑 ",
                "n": 8541
            }
        ],
        "special_key": "中国新歌声第二季",
        "special_url": "https://y.qq.com/m/act/singchina2/index.html?ADTAG=search"
    },
    "subcode": 0
}